libcst_mypy/__init__.py
libcst_mypy/provider.py
libcst_mypy/utils.py
mypy_type_inference-0.0.0.dist-info/METADATA
mypy_type_inference-0.0.0.dist-info/WHEEL
mypy_type_inference-0.0.0.dist-info/licenses/LICENSE
mypy_type_inference-0.0.0.dist-info/RECORD
